pymc_bart_rs-0.1.2.dist-info/METADATA
pymc_bart_rs-0.1.2.dist-info/WHEEL
pymc_bart/compile_pymc.py
pymc_bart/pgbart.py
pymc_bart/__init__.py
pymc_bart/bart.py
pymc_bart/utils.py
pymc_bart/pymc_bart.cpython-38-x86_64-linux-gnu.so
pymc_bart_rs-0.1.2.dist-info/RECORD
