Metadata-Version: 2.4
Name: pymc_bart_rs
Version: 0.1.2
Classifier: Programming Language :: Rust
Classifier: Programming Language :: Python :: Implementation :: CPython
Classifier: Programming Language :: Python :: Implementation :: PyPy
Requires-Dist: numba >=0.60.0 ; extra == 'all'
Requires-Dist: pymc >=5.19.1 ; extra == 'all'
Requires-Dist: arviz >=0.20.0 ; extra == 'all'
Provides-Extra: all
Summary: Rust implementation of Bayesian Additive Regression Trees for Probabilistic programming with PyMC
Requires-Python: >=3.8, <3.13
